pCrunch/__init__.py
pCrunch/aeroelastic_output.py
pCrunch/crunch.py
pCrunch/fatigue.py
pCrunch/openfast_readers.py
pCrunch/utility.py
pCrunch/test/__init__.py
pCrunch/test/test_aeroelastic_output.py
pCrunch/test/test_crunch.py
pCrunch/test/test_example.py
pCrunch/test/test_fatigue.py
pCrunch/test/test_parsers.py
pCrunch/test/data/AOC_WSt.out
pCrunch/test/data/AOC_WSt.outb
pCrunch/test/data/DLC2.3_1.out
pCrunch/test/data/DLC2.3_2.out
pCrunch/test/data/DLC2.3_3.out
pCrunch/test/data/Test1.outb
pCrunch/test/data/Test2.outb
pCrunch/test/data/Test3.outb
pCrunch/test/data/__init__.py
pCrunch/test/data/step_0.outb
pCrunch/test/data/DLC1p1/DLC1.1_0_NREL5MW_OC3_spar_0.outb
pCrunch/test/data/DLC1p1/DLC1.1_0_NREL5MW_OC3_spar_1.outb
pCrunch/test/data/DLC1p1/DLC1.1_0_NREL5MW_OC3_spar_2.outb
pCrunch/test/data/DLC1p1/DLC1.1_0_NREL5MW_OC3_spar_3.outb
pCrunch/test/data/DLC1p1/DLC1.1_0_NREL5MW_OC3_spar_4.outb
pCrunch/test/data/DLC1p1/case_matrix_DLC1.1_0.txt
pCrunch/test/data/DLC1p1/case_matrix_combined.txt
pcrunch-2.1.4.dist-info/licenses/LICENSE.txt
pcrunch-2.1.4.dist-info/METADATA
pcrunch-2.1.4.dist-info/WHEEL
pcrunch-2.1.4.dist-info/top_level.txt
pcrunch-2.1.4.dist-info/RECORD
