Metadata-Version: 2.4
Name: pCrunch
Version: 2.1.4
Summary: IO and Post Processing for generic time series data of multibody aeroelastic wind turbine simulations.
Author-email: NREL WISDEM Team <systems.engineering@nrel.gov>
License: Apache-2.0
Project-URL: Homepage, https://github.com/NREL/pCrunch
Keywords: wind,turbine,fatigue,ultimate,aeroelastic
Classifier: Development Status :: 4 - Beta
Classifier: Intended Audience :: Science/Research
Classifier: Topic :: Scientific/Engineering
Classifier: License :: OSI Approved :: Apache Software License
Classifier: Programming Language :: Python :: 3
Classifier: Programming Language :: Python :: 3.9
Classifier: Programming Language :: Python :: 3.10
Classifier: Programming Language :: Python :: 3.11
Classifier: Programming Language :: Python :: 3.12
Classifier: Programming Language :: Python :: 3.13
Classifier: Programming Language :: Python :: 3.14
Classifier: Programming Language :: Python :: 3 :: Only
Classifier: Operating System :: Microsoft :: Windows
Classifier: Operating System :: POSIX :: Linux
Classifier: Operating System :: POSIX
Classifier: Operating System :: Unix
Classifier: Operating System :: MacOS
Requires-Python: >=3.9
License-File: LICENSE.txt
Requires-Dist: fatpack
Requires-Dist: numpy
Requires-Dist: pandas
Requires-Dist: pyyaml
Requires-Dist: ruamel.yaml
Requires-Dist: scipy
Requires-Dist: numexpr
Provides-Extra: test
Requires-Dist: pytest; extra == "test"
Requires-Dist: pytest-cov; extra == "test"
Requires-Dist: treon; extra == "test"
Provides-Extra: docs
Requires-Dist: sphinx; extra == "docs"
Requires-Dist: sphinx_rtd_theme; extra == "docs"
Dynamic: license-file
